[1,["49n06g7i5EU4m5WNY28JRy","b4BGOB7CdIs5cIPMFaJmjX","ccNXA6ahdEzLEAPFsmkXoT","ecpdLyjvZBwrvm+cedCcQy","f6rQ019QtFiJTpXt5kBpwK","cbIC2OGrpBLqgQfEjHqiP1","a6D+dydhhBDJ0E+lKS9lpp","731R863HJEL4QsC98lNwEd","5e1rpSieVM2ZR0dcGzv97t","99Mnyx8mJCMbBHEE4rGED3","eaYE4Te2ZAO6HA2WwJ/UpF"],["_textureSetter","value","node","root","data","_spriteFrame","_defaultClip"],["cc.SpriteFrame",["cc.Prefab",["_name"],2],["cc.Node",["_name","_groupIndex","_components","_prefab","_contentSize","_trs"],1,9,4,5,7],["cc.Sprite",["_sizeMode","_isTrimmedMode","node","_materials","_spriteFrame"],1,1,3,6],["cc.CircleCollider",["node"],3,1],["d5f74pedANPgZfCbRgBd3/a",["node"],3,1],["cc.Animation",["node","_clips","_defaultClip"],3,1,3,6],["cc.PrefabInfo",["root"],3,1],["cc.AnimationClip",["_name","_duration","sample","wrapMode","curveData"],-1,11]],[[1,0,2],[2,0,1,2,3,4,5,3],[3,0,1,2,3,4,3],[4,0,1],[5,0,1],[6,0,1,2,1],[7,0,1],[8,0,1,2,3,4,5]],[[[{"name":"Boss13_Attack_05","rect":[2,724,84,124],"offset":[-1,1],"originalSize":[100,150],"rotated":1,"capInsets":[0,0,0,0]}],[0],0,[0],[0],[0]],[[{"name":"Boss13_Attack_04","rect":[662,746,80,120],"offset":[-2,2],"originalSize":[100,150],"rotated":1,"capInsets":[0,0,0,0]}],[0],0,[0],[0],[0]],[[[0,"50801"],[1,"50801",9,[[2,2,false,-2,[0],1],[3,-3],[4,-4],[5,-5,[3],2]],[6,-1],[5,100,150],[0,0,0,0,0,0,1,1.5,1.5,1]]],0,[0,3,1,0,2,1,0,2,1,0,2,1,0,2,1,0,4,1,5],[0,0,0,0],[-1,5,6,-1],[3,1,2,2]],[[{"name":"Boss13_Attack_06","rect":[370,692,88,128],"offset":[5,3],"originalSize":[100,150],"rotated":1,"capInsets":[0,0,0,0]}],[0],0,[0],[0],[0]],[[{"name":"Boss13_Attack_03","rect":[938,652,82,116],"offset":[-4,5],"originalSize":[100,150],"capInsets":[0,0,0,0]}],[0],0,[0],[0],[0]],[[{"name":"Boss13_Attack_00","rect":[304,782,94,112],"offset":[2,6],"originalSize":[100,150],"rotated":1,"capInsets":[0,0,0,0]}],[0],0,[0],[0],[0]],[[{"name":"Boss13_Attack_02","rect":[308,882,80,114],"offset":[0,6],"originalSize":[100,150],"capInsets":[0,0,0,0]}],[0],0,[0],[0],[0]],[[[7,"e50801",0.26666666666666666,30,2,[{},"comps",11,[{},"cc.Sprite",11,[{},"spriteFrame",12,[[[{"frame":0},"value",6,0],[{"frame":0.03333333333333333},"value",6,1],[{"frame":0.06666666666666667},"value",6,2],[{"frame":0.1},"value",6,3],[{"frame":0.13333333333333333},"value",6,4],[{"frame":0.16666666666666666},"value",6,5],[{"frame":0.2},"value",6,6],[{"frame":0.23333333333333334},"value",6,7]],11,11,11,11,11,11,11,11]]]]]],0,0,[0,0,0,0,0,0,0,0],[1,1,1,1,1,1,1,1],[1,4,5,6,7,8,9,10]],[[{"name":"Boss13_Attack_07","rect":[724,626,90,118],"offset":[5,12],"originalSize":[100,150],"capInsets":[0,0,0,0]}],[0],0,[0],[0],[0]],[[{"name":"Boss13_Attack_01","rect":[724,512,92,112],"offset":[2,5],"originalSize":[100,150],"capInsets":[0,0,0,0]}],[0],0,[0],[0],[0]]]]