[1,["568qJr+jBCh7/OVYVNXszY","a18CLkg5pGAoTnK8xTqfFx","c9q7OKd4xK4L/6CPfOCSSZ","ecpdLyjvZBwrvm+cedCcQy","64fMuLU8NJIYjKgB2TMAOe","d7tfjxUShC+4LiAZHgvMsF","a2pZ3yYA1J3pmA3q/96vJh","d2S/LxQu9CQK2xMIhdU4xc","2aRNWoeKlNbISrPhhB1l+d","4c8VGX5r1KkL4ap3QkvwOX","25w/qYJ/hHFplS5Xl69IKF"],["_textureSetter","value","node","root","data","_spriteFrame","_defaultClip"],["cc.SpriteFrame",["cc.Prefab",["_name"],2],["cc.Node",["_name","_components","_prefab","_contentSize","_anchorPoint"],2,9,4,5,5],["cc.Sprite",["_sizeMode","_isTrimmedMode","node","_materials","_spriteFrame"],1,1,3,6],["cc.Animation",["node","_clips","_defaultClip"],3,1,3,6],["cc.PrefabInfo",["root","asset"],3,1,1],["cc.AnimationClip",["_name","_duration","sample","curveData"],0,11]],[[1,0,2],[2,0,1,2,3,4,2],[3,0,1,2,3,4,3],[4,0,1,2,1],[5,0,1,1],[6,0,1,2,3,4]],[[[{"name":"Boss14_Bao_07","rect":[204,1594,298,160],"offset":[1,2],"originalSize":[300,200],"rotated":1,"capInsets":[0,0,0,0]}],[0],0,[0],[0],[0]],[[{"name":"Boss14_Bao_05","rect":[402,2,298,172],"offset":[1,3],"originalSize":[300,200],"rotated":1,"capInsets":[0,0,0,0]}],[0],0,[0],[0],[0]],[[{"name":"Boss14_Bao_06","rect":[2,2000,42,48],"offset":[-126,58],"originalSize":[300,200],"rotated":1,"capInsets":[0,0,0,0]}],[0],0,[0],[0],[0]],[[{"name":"Boss14_Bao_01","rect":[476,1886,204,158],"offset":[17,-7],"originalSize":[300,200],"capInsets":[0,0,0,0]}],[0],0,[0],[0],[0]],[[{"name":"Boss14_Bao_00","rect":[622,639,116,110],"offset":[10,-28],"originalSize":[300,200],"rotated":1,"capInsets":[0,0,0,0]}],[0],0,[0],[0],[0]],[[{"name":"Boss14_Bao_03","rect":[402,766,280,170],"offset":[10,0],"originalSize":[300,200],"rotated":1,"capInsets":[0,0,0,0]}],[0],0,[0],[0],[0]],[[[0,"50932"],[1,"50932",[[2,2,false,-2,[0],1],[3,-3,[3],2]],[4,-1,0],[5,300,200],[0,0.5,0.2]]],0,[0,3,1,0,2,1,0,2,1,0,4,1,3],[0,0,0,0],[-1,5,6,-1],[3,1,2,2]],[[[5,"e50932",0.26666666666666666,30,[{},"comps",11,[{},"cc.Sprite",11,[{},"spriteFrame",12,[[[{"frame":0},"value",6,0],[{"frame":0.03333333333333333},"value",6,1],[{"frame":0.06666666666666667},"value",6,2],[{"frame":0.1},"value",6,3],[{"frame":0.13333333333333333},"value",6,4],[{"frame":0.16666666666666666},"value",6,5],[{"frame":0.2},"value",6,6],[{"frame":0.23333333333333334},"value",6,7]],11,11,11,11,11,11,11,11]]]]]],0,0,[0,0,0,0,0,0,0,0],[1,1,1,1,1,1,1,1],[1,4,5,6,7,8,9,10]],[[{"name":"Boss14_Bao_04","rect":[366,1594,290,174],"offset":[5,2],"originalSize":[300,200],"rotated":1,"capInsets":[0,0,0,0]}],[0],0,[0],[0],[0]],[[{"name":"Boss14_Bao_02","rect":[406,1228,270,168],"offset":[14,-3],"originalSize":[300,200],"rotated":1,"capInsets":[0,0,0,0]}],[0],0,[0],[0],[0]]]]